README.md
alertHandler.log
config.yaml
setup.py
./alertHandler.log
supervisor_discord.egg-info/PKG-INFO
supervisor_discord.egg-info/SOURCES.txt
supervisor_discord.egg-info/dependency_links.txt
supervisor_discord.egg-info/entry_points.txt
supervisor_discord.egg-info/requires.txt
supervisor_discord.egg-info/top_level.txt
supervisordiscord/__init__.py
supervisordiscord/alertHandler.log
supervisordiscord/alertHandler.py
supervisordiscord/autoconfig.py
supervisordiscord/testCrash.py