Metadata-Version: 2.1
Name: supervisor-discord
Version: 1.3
Summary: Connect supervisor to discord via webhooks
Home-page: https://github.com/chaosay/supervisor-discord
Author: chaos_a
License: GNU GPL v3
Download-URL: https://github.com/chaosay/supervisor-discord/archive/1.3.tar.gz
Keywords: supervisor,discord,alerts
Platform: UNKNOWN
Classifier: Development Status :: 4 - Beta
Classifier: Intended Audience :: System Administrators
Classifier: Topic :: System :: Boot
Classifier: Topic :: System :: Monitoring
Classifier: Topic :: System :: Systems Administration
Classifier: License :: OSI Approved :: GNU General Public License v3 or later (GPLv3+)
Classifier: Programming Language :: Python :: 3
Classifier: Programming Language :: Python :: 3.4
Classifier: Programming Language :: Python :: 3.5
Classifier: Programming Language :: Python :: 3.7
